trinomial/__init__.py
trinomial/trinomial.py
trinomial-0.0.3.dist-info/LICENSE
trinomial-0.0.3.dist-info/METADATA
trinomial-0.0.3.dist-info/WHEEL
trinomial-0.0.3.dist-info/top_level.txt
trinomial-0.0.3.dist-info/RECORD
