Metadata-Version: 2.1
Name: trinomial
Version: 0.0.3
Summary: A simple name anonymization library
Home-page: https://github.com/caltechlibrary/trinomial
Author: Michael Hucka
Author-email: mhucka@library.caltech.edu
License: BSD 3-clause
Project-URL: Source Code, https://github.com/caltechlibrary/trinomial
Project-URL: Bug Tracker, https://github.com/caltechlibrary/trinomial/issues
Keywords: Python,utilities
Platform: UNKNOWN
Classifier: Development Status :: 2 - Pre-Alpha
Classifier: Intended Audience :: Science/Research
Classifier: License :: OSI Approved :: BSD License
Classifier: Operating System :: MacOS :: MacOS X
Classifier: Operating System :: POSIX
Classifier: Operating System :: POSIX :: Linux
Classifier: Operating System :: Unix
Classifier: Operating System :: Microsoft :: Windows
Classifier: Programming Language :: Python
Classifier: Programming Language :: Python :: 3.8
Requires-Python: >=3.8
License-File: LICENSE
